whatstyle.py
whatstyle-0.1.9.dist-info/LICENSE
whatstyle-0.1.9.dist-info/METADATA
whatstyle-0.1.9.dist-info/WHEEL
whatstyle-0.1.9.dist-info/entry_points.txt
whatstyle-0.1.9.dist-info/top_level.txt
whatstyle-0.1.9.dist-info/RECORD
