Metadata-Version: 2.1
Name: whatstyle
Version: 0.1.9
Summary: whatstyle finds a code format style that fits given source files.
Home-page: https://github.com/mikr/whatstyle
Author: Michael Krause
Author-email: michael@krause-software.com
License: MIT
Keywords: formatter beautifier clang-format yapf tidy indent astyle uncrustify scalariform scalafmt rfmt rustfmt
Platform: any
Classifier: Development Status :: 4 - Beta
Classifier: Environment :: Console
Classifier: Intended Audience :: Developers
Classifier: License :: OSI Approved :: MIT License
Classifier: Natural Language :: English
Classifier: Operating System :: OS Independent
Classifier: Programming Language :: Python :: 2.7
Classifier: Programming Language :: Python :: 3.4
Classifier: Programming Language :: Python :: 3.5
Classifier: Programming Language :: Python :: 3.6
Classifier: Programming Language :: Python :: 3.7
Classifier: Programming Language :: Python :: 3.8
Classifier: Programming Language :: Python :: 3.9
Classifier: Topic :: Software Development :: Libraries :: Python Modules
Classifier: Topic :: Software Development :: Quality Assurance
Classifier: Topic :: Utilities
